ir_amplitude_detuning/__init__.py
ir_amplitude_detuning/lhc_detuning_corrections.py
ir_amplitude_detuning/setup_template.py
ir_amplitude_detuning/detuning/__init__.py
ir_amplitude_detuning/detuning/calculations.py
ir_amplitude_detuning/detuning/equation_system.py
ir_amplitude_detuning/detuning/measurements.py
ir_amplitude_detuning/detuning/targets.py
ir_amplitude_detuning/detuning/terms.py
ir_amplitude_detuning/plotting/__init__.py
ir_amplitude_detuning/plotting/correctors.py
ir_amplitude_detuning/plotting/detuning.py
ir_amplitude_detuning/plotting/utils.py
ir_amplitude_detuning/simulation/__init__.py
ir_amplitude_detuning/simulation/lhc_simulation.py
ir_amplitude_detuning/simulation/results_loader.py
ir_amplitude_detuning/utilities/__init__.py
ir_amplitude_detuning/utilities/common.py
ir_amplitude_detuning/utilities/constants.py
ir_amplitude_detuning/utilities/correctors.py
ir_amplitude_detuning/utilities/latex.py
ir_amplitude_detuning/utilities/logging.py
ir_amplitude_detuning/utilities/measurement_analysis.py
ir_amplitude_detuning-1.0.0.dist-info/METADATA
ir_amplitude_detuning-1.0.0.dist-info/WHEEL
ir_amplitude_detuning-1.0.0.dist-info/licenses/LICENSE
ir_amplitude_detuning-1.0.0.dist-info/RECORD
