Metadata-Version: 2.4
Name: ir_amplitude_detuning
Version: 1.0.0
Summary: Python tools to correct amplitude detuning in the insertion regions of a particle accelerator.
Project-URL: homepage, https://github.com/pylhc/ir_amplitude_detuning
Project-URL: repository, https://github.com/pylhc/ir_amplitude_detuning
Project-URL: documentation, https://pylhc.github.io/ir_amplitude_detuning/
Project-URL: changelog, https://github.com/pylhc/ir_amplitude_detuning/blob/master/CHANGELOG.md
Author-email: OMC Team <pylhc@github.com>
License-Expression: MIT
License-File: LICENSE
Classifier: Intended Audience :: Science/Research
Classifier: License :: OSI Approved :: MIT License
Classifier: Natural Language :: English
Classifier: Operating System :: OS Independent
Classifier: Programming Language :: Python :: 3 :: Only
Classifier: Programming Language :: Python :: 3.10
Classifier: Programming Language :: Python :: 3.11
Classifier: Programming Language :: Python :: 3.12
Classifier: Programming Language :: Python :: 3.13
Classifier: Programming Language :: Python :: Implementation :: CPython
Classifier: Topic :: Scientific/Engineering
Classifier: Topic :: Scientific/Engineering :: Physics
Classifier: Topic :: Scientific/Engineering :: Visualization
Classifier: Topic :: Software Development :: Libraries :: Python Modules
Classifier: Typing :: Typed
Requires-Python: >=3.10
Requires-Dist: cpymad-lhc>=0.2.1
Requires-Dist: cpymad>=1.17.0
Requires-Dist: cvxpy>=1.5
Requires-Dist: matplotlib>=3.8
Requires-Dist: numpy>=1.24
Requires-Dist: omc3>=0.24
Requires-Dist: optics-functions>=0.1
Requires-Dist: pandas>=2.1
Requires-Dist: tfs-pandas>=3.8
Provides-Extra: all
Requires-Dist: gitpython>=3.1; extra == 'all'
Requires-Dist: pytest-cov>=2.9; extra == 'all'
Requires-Dist: pytest-dependency>=0.6.0; extra == 'all'
Requires-Dist: pytest-timeout>=1.4; extra == 'all'
Requires-Dist: pytest>=7.0; extra == 'all'
Requires-Dist: sphinx-codeautolink>=0.14; extra == 'all'
Requires-Dist: sphinx-copybutton>=0.4; extra == 'all'
Requires-Dist: sphinx-prompt>=1.7; extra == 'all'
Requires-Dist: sphinx-rtd-theme>=2.0; extra == 'all'
Requires-Dist: sphinx>=7.0; extra == 'all'
Provides-Extra: doc
Requires-Dist: sphinx-codeautolink>=0.14; extra == 'doc'
Requires-Dist: sphinx-copybutton>=0.4; extra == 'doc'
Requires-Dist: sphinx-prompt>=1.7; extra == 'doc'
Requires-Dist: sphinx-rtd-theme>=2.0; extra == 'doc'
Requires-Dist: sphinx>=7.0; extra == 'doc'
Provides-Extra: test
Requires-Dist: gitpython>=3.1; extra == 'test'
Requires-Dist: pytest-cov>=2.9; extra == 'test'
Requires-Dist: pytest-dependency>=0.6.0; extra == 'test'
Requires-Dist: pytest-timeout>=1.4; extra == 'test'
Requires-Dist: pytest>=7.0; extra == 'test'
